Metadata-Version: 1.0
Name: SongRecognition
Version: 0.4
Summary: Song Recognition will listen to your song lyrics and will result in a song that you can play in youtube as well
Home-page: https://github.com/manavrawat10/SongRecognition
Author: Manvenddra Rawat
Author-email: manvenddra.rawat@gmail.com
License: Manvenddra
Platform: UNKNOWN
